shotgun/__init__.py
shotgun/api_endpoints.py
shotgun/build_constants.py
shotgun/exceptions.py
shotgun/logging_config.py
shotgun/main.py
shotgun/posthog_telemetry.py
shotgun/py.typed
shotgun/settings.py
shotgun/telemetry.py
shotgun/agents/__init__.py
shotgun/agents/agent_manager.py
shotgun/agents/cancellation.py
shotgun/agents/common.py
shotgun/agents/export.py
shotgun/agents/file_read.py
shotgun/agents/gemini3_patch.py
shotgun/agents/llm.py
shotgun/agents/messages.py
shotgun/agents/models.py
shotgun/agents/plan.py
shotgun/agents/research.py
shotgun/agents/runner.py
shotgun/agents/specify.py
shotgun/agents/tasks.py
shotgun/agents/usage_manager.py
shotgun/agents/config/README.md
shotgun/agents/config/__init__.py
shotgun/agents/config/constants.py
shotgun/agents/config/manager.py
shotgun/agents/config/models.py
shotgun/agents/config/provider.py
shotgun/agents/config/streaming_test.py
shotgun/agents/constants/__init__.py
shotgun/agents/constants/file_types.py
shotgun/agents/context_analyzer/__init__.py
shotgun/agents/context_analyzer/analyzer.py
shotgun/agents/context_analyzer/constants.py
shotgun/agents/context_analyzer/formatter.py
shotgun/agents/context_analyzer/models.py
shotgun/agents/conversation/__init__.py
shotgun/agents/conversation/filters.py
shotgun/agents/conversation/manager.py
shotgun/agents/conversation/models.py
shotgun/agents/conversation/history/__init__.py
shotgun/agents/conversation/history/chunking.py
shotgun/agents/conversation/history/compaction.py
shotgun/agents/conversation/history/constants.py
shotgun/agents/conversation/history/context_extraction.py
shotgun/agents/conversation/history/file_content_deduplication.py
shotgun/agents/conversation/history/history_building.py
shotgun/agents/conversation/history/history_processors.py
shotgun/agents/conversation/history/message_utils.py
shotgun/agents/conversation/history/token_estimation.py
shotgun/agents/conversation/history/token_counting/__init__.py
shotgun_sh-0.7.7.dist-info/METADATA
shotgun_sh-0.7.7.dist-info/WHEEL
shotgun_sh-0.7.7.dist-info/entry_points.txt
shotgun_sh-0.7.7.dist-info/licenses/LICENSE
shotgun_sh-0.7.7.dist-info/RECORD
