Metadata-Version: 2.4
Name: shotgun-sh
Version: 0.7.7
Summary: AI-powered research, planning, and task management CLI tool
Project-URL: Homepage, https://shotgun.sh/
Project-URL: Repository, https://github.com/shotgun-sh/shotgun
Project-URL: Issues, https://github.com/shotgun-sh/shotgun-alpha/issues
Project-URL: Discord, https://discord.gg/5RmY6J2N7s
Author-email: "Proofs.io" <hello@proofs.io>
License: MIT
License-File: LICENSE
Keywords: agent,ai,cli,llm,planning,productivity,pydantic-ai,research,task-management
Classifier: Development Status :: 4 - Beta
Classifier: Environment :: Console
Classifier: Intended Audience :: Developers
Classifier: License :: OSI Approved :: MIT License
Classifier: Operating System :: OS Independent
Classifier: Programming Language :: Python :: 3
Classifier: Programming Language :: Python :: 3.11
Classifier: Programming Language :: Python :: 3.12
Classifier: Topic :: Software Development :: Libraries :: Python Modules
Classifier: Topic :: Utilities
Requires-Python: <3.14,>=3.11
Requires-Dist: aiofiles>=24.0.0
Requires-Dist: anthropic>=0.39.0
Requires-Dist: dependency-injector>=4.41.0
Requires-Dist: genai-prices>=0.0.27
Requires-Dist: httpx>=0.27.0
Requires-Dist: jinja2>=3.1.0
Requires-Dist: logfire>=2.0.0
Requires-Dist: openai>=1.0.0
Requires-Dist: packaging>=23.0
Requires-Dist: pathspec>=0.12.0
Requires-Dist: posthog>=3.0.0
Requires-Dist: psutil>=5.9.0
Requires-Dist: pydantic-ai==1.44.0
Requires-Dist: pydantic-settings>=2.0.0
Requires-Dist: pyperclip>=1.10.0
Requires-Dist: real-ladybug==0.14.1
Requires-Dist: rich>=13.0.0
Requires-Dist: sentencepiece>=0.2.0
Requires-Dist: tenacity>=8.0.0
Requires-Dist: textual-serve>=0.1.0
Requires-Dist: textual>=6.1.0
Requires-Dist: tiktoken>=0.7.0
Requires-Dist: tree-sitter-go>=0.23.0
Requires-Dist: tree-sitter-javascript>=0.23.0
Requires-Dist: tree-sitter-python>=0.23.0
Requires-Dist: tree-sitter-rust>=0.23.0
Requires-Dist: tree-sitter-typescript>=0.23.0
Requires-Dist: tree-sitter>=0.21.0
Requires-Dist: typer>=0.12.0
Requires-Dist: watchdog>=4.0.0
